general_functions0913/__init__.py
general_functions0913-1.1.0.dist-info/METADATA
general_functions0913-1.1.0.dist-info/WHEEL
general_functions0913-1.1.0.dist-info/top_level.txt
general_functions0913-1.1.0.dist-info/RECORD
