Metadata-Version: 2.1
Name: general_functions0913
Version: 1.1.0
Summary: this sdk is a working protype with file encryption
Author: rishabh_sharma
Author-email: rishabhsharmabwr@gmail.com
